prompter/__init__.py
prompter/__init__.pyc
prompter/_version.py
prompter/_version.pyc
prompter-0.3.10.dist-info/DESCRIPTION.rst
prompter-0.3.10.dist-info/METADATA
prompter-0.3.10.dist-info/RECORD
prompter-0.3.10.dist-info/WHEEL
prompter-0.3.10.dist-info/metadata.json
prompter-0.3.10.dist-info/top_level.txt
tests/__init__.py
tests/test_prompt.py
tests/test_yesno.py
