Metadata-Version: 2.0
Name: prompter
Version: 0.3.10
Summary: Simple CUI input prompt
Home-page: https://github.com/tylerdave/prompter
Author: Dave Forgac
Author-email: tylerdave@tylerdave.com
License: MIT
Platform: UNKNOWN
Classifier: Development Status :: 3 - Alpha
Classifier: Environment :: Console
Classifier: License :: OSI Approved :: MIT License
Classifier: Operating System :: OS Independent
Classifier: Programming Language :: Python
Classifier: Programming Language :: Python :: 2.6
Classifier: Programming Language :: Python :: 2.7
Classifier: Programming Language :: Python :: 3
Classifier: Programming Language :: Python :: 3.2
Classifier: Programming Language :: Python :: 3.3
